TkinterExtensions/Enumerations.py
TkinterExtensions/Events.py
TkinterExtensions/HID_BUFFER.py
TkinterExtensions/Mixins.py
TkinterExtensions/__init__.py
TkinterExtensions/__version__.py
TkinterExtensions/debug.py
TkinterExtensions/examples.py
TkinterExtensions/Widgets/AnimatedGIF.py
TkinterExtensions/Widgets/AutoScroll.py
TkinterExtensions/Widgets/BaseApp.py
TkinterExtensions/Widgets/BaseWidgets.py
TkinterExtensions/Widgets/Custom.py
TkinterExtensions/Widgets/Frames.py
TkinterExtensions/Widgets/HTML.py
TkinterExtensions/Widgets/KeyBoard.py
TkinterExtensions/Widgets/KeyboardComboBoxThemed.py
TkinterExtensions/Widgets/KeyboardEntry.py
TkinterExtensions/Widgets/Root.py
TkinterExtensions/Widgets/Style.py
TkinterExtensions/Widgets/Themed.py
TkinterExtensions/Widgets/Widgets.py
TkinterExtensions/Widgets/__init__.py
TkinterExtensions/Widgets/base.py
TkinterExtensions/Widgets/tkMessageBox.py
TkinterExtensions-1.9.9.dist-info/LICENSE.md
TkinterExtensions-1.9.9.dist-info/METADATA
TkinterExtensions-1.9.9.dist-info/WHEEL
TkinterExtensions-1.9.9.dist-info/top_level.txt
TkinterExtensions-1.9.9.dist-info/RECORD
