Metadata-Version: 2.1
Name: TkinterExtensions
Version: 1.9.9
Summary: Strongly typed widgets and event with multiple built in helper functions to speed up development.
Home-page: https://github.com/Jakar510/TkinterExtensions
Author: Tyler Stegmaier
Author-email: tyler.stegmaier.510@gmail.com
Maintainer: Tyler Stegmaier
Maintainer-email: tyler.stegmaier.510@gmail.com
License: MIT
Keywords: TkinterExtensions Tkinter Extensions tk ttk tkinter
Platform: UNKNOWN
Classifier: Development Status :: 4 - Beta
Classifier: Intended Audience :: Developers
Classifier: Topic :: Software Development :: Build Tools
Classifier: License :: Free To Use But Restricted
Classifier: Operating System :: MacOS
Classifier: Operating System :: Microsoft :: Windows
Classifier: Operating System :: POSIX
Classifier: Programming Language :: Python :: 3
Requires-Dist: pillow (>=8.1.0)
Requires-Dist: tk-html-widgets (>=0.4.0)
Requires-Dist: PythonDebugTools (>=2.2.3)
Requires-Dist: BaseExtensions (>=1.2.6)
